setup.py
adys/__init__.py
adys/bn2smv.py
adys/bnutils.py
adys/models.py
adys/setup.py
adys/utils.py
adys.egg-info/PKG-INFO
adys.egg-info/SOURCES.txt
adys.egg-info/dependency_links.txt
adys.egg-info/requires.txt
adys.egg-info/top_level.txt
dist/adys-0.1.4.tar.gz
dist/adys-0.1.5.tar.gz