Metadata-Version: 1.1
Name: adys
Version: 0.1.6
Summary: Simple python library for Boolean networks
Home-page: UNKNOWN
Author: Loïc Paulevé
Author-email: loic.pauleve@lri.fr
License: CeCILL
Keywords: boolean networks,model checing,teaching
Platform: UNKNOWN
Classifier: Intended Audience :: Science/Research
Classifier: Topic :: Scientific/Engineering :: Bio-Informatics
